shootpandora/__init__.py
shootpandora/__main__.py
shootpandora/cloud_launcher.py
shootpandora/launcher.py
shootpandora/py.typed
shootpandora/bots/__init__.py
shootpandora/bots/legacy.py
shootpandora/bots/server.py
shootpandora/exts/__init__.py
shootpandora/exts/config.py
shootpandora/exts/hooks.py
shootpandora/exts/sentry.py
shootpandora/exts/token.py
shootpandora/flask/static/apple-touch-icon.png
shootpandora/flask/static/favicon-16x16.png
shootpandora/flask/static/favicon-32x32.png
shootpandora/flask/static/_next/static/chunks/113-23682f80a24dd00d.js
shootpandora/flask/static/_next/static/chunks/14-0cb0d20affbd720d.js
shootpandora/flask/static/_next/static/chunks/174-bd28069f281ef76f.js
shootpandora/flask/static/_next/static/chunks/1f110208-44a6f43ddc5e9011.js
shootpandora/flask/static/_next/static/chunks/264-13e92c51b0315184.js
shootpandora/flask/static/_next/static/chunks/360-442b869f1ba4bb1b.js
shootpandora/flask/static/_next/static/chunks/424-d1d3bfe6a3ca6c4a.js
shootpandora/flask/static/_next/static/chunks/554.9b8bfd0762461d74.js
shootpandora/flask/static/_next/static/chunks/68a27ff6-1185184b61bc22d0.js
shootpandora/flask/static/_next/static/chunks/762-222df1028c0c1555.js
shootpandora/flask/static/_next/static/chunks/949.1a6eb804b5e91f61.js
shootpandora/flask/static/_next/static/chunks/bd26816a-981e1ddc27b37cc6.js
shootpandora/flask/static/_next/static/chunks/framework-7a789ee31d2a7534.js
shootpandora/flask/static/_next/static/chunks/main-149b337e061b4d04.js
shootpandora/flask/static/_next/static/chunks/polyfills-c67a75d1b6f99dc8.js
shootpandora/flask/static/_next/static/chunks/webpack-c9a868e8e0796ec6.js
shootpandora/flask/static/_next/static/chunks/pages/_app-aaa11de1926dcafe.js
shootpandora/flask/static/_next/static/chunks/pages/_error-786d27d84962122a.js
shootpandora/flask/static/_next/static/chunks/pages/chat/[[...chatId]]-76751174916fa3f7.js
shootpandora/flask/static/_next/static/css/ac221fb2caad35a6.css
shootpandora_ChatGPT-20230725.1.4.dist-info/LICENSE
shootpandora_ChatGPT-20230725.1.4.dist-info/METADATA
shootpandora_ChatGPT-20230725.1.4.dist-info/WHEEL
shootpandora_ChatGPT-20230725.1.4.dist-info/entry_points.txt
shootpandora_ChatGPT-20230725.1.4.dist-info/top_level.txt
shootpandora_ChatGPT-20230725.1.4.dist-info/RECORD
