Metadata-Version: 2.1
Name: shootpandora-ChatGPT
Version: 20230725.1.4
Summary: A command-line interface to ChatGPT
Home-page: https://github.com/shoot82003/shootpandora
Author: XiaoZhou Huang
Author-email: shoot82003@qq.com
Project-URL: Source, https://github.com/shoot82003/shootpandora
Project-URL: Tracker, https://github.com/shoot82003/shootpandora/issues
Keywords: OpenAI ChatGPT ChatGPT-Plus gpt-3.5-turbo gpt-3.5-turbo-0301
Classifier: Development Status :: 5 - Production/Stable
Classifier: Environment :: Console
Classifier: Environment :: Web Environment
Classifier: Framework :: Flask
Classifier: Intended Audience :: Developers
Classifier: Intended Audience :: End Users/Desktop
Classifier: License :: OSI Approved :: GNU General Public License v2 (GPLv2)
Classifier: Natural Language :: English
Classifier: Natural Language :: Chinese (Simplified)
Classifier: Operating System :: MacOS
Classifier: Operating System :: Microsoft :: Windows
Classifier: Operating System :: POSIX :: Linux
Classifier: Programming Language :: SQL
Classifier: Programming Language :: JavaScript
Classifier: Programming Language :: Python :: 3.7
Classifier: Programming Language :: Python :: 3.8
Classifier: Programming Language :: Python :: 3.9
Classifier: Programming Language :: Python :: 3.10
Classifier: Programming Language :: Python :: 3.11
Classifier: Topic :: Communications :: Chat
Classifier: Topic :: Internet :: WWW/HTTP
Requires-Python: >=3.7
License-File: LICENSE
Requires-Dist: certifi
Requires-Dist: httpx[socks] (~=0.23.3)
Requires-Dist: requests[socks] (~=2.28.2)
Requires-Dist: rich (~=13.3.2)
Requires-Dist: appdirs (~=1.4.4)
Requires-Dist: werkzeug (~=2.2.3)
Requires-Dist: flask[async] (~=2.2.3)
Requires-Dist: flask-cors (~=3.0.10)
Requires-Dist: waitress (~=2.1.2)
Requires-Dist: loguru (~=0.6.0)
Requires-Dist: sentry-sdk (~=1.17.0)
Requires-Dist: pyjwt[crypto] (~=2.6.0)
Requires-Dist: pyperclip (~=1.8.2)
Requires-Dist: pyreadline3 (~=3.4.0) ; platform_system == "Windows"
Provides-Extra: api
Requires-Dist: shootpandora-ChatGPT (~=20230725.1.4) ; extra == 'api'
Requires-Dist: sqlalchemy (~=2.0.7) ; extra == 'api'
Requires-Dist: yoyo-migrations (~=8.2.0) ; extra == 'api'
Provides-Extra: cloud
Requires-Dist: shootpandora-cloud (~=20230725.1.4) ; extra == 'cloud'
